deckbuilder/__init__.py
deckbuilder/cli.py
deckbuilder/layout_intelligence.json
deckbuilder/assets/html_colors_reference.html
deckbuilder/assets/master_default_presentation.json
deckbuilder/assets/master_default_presentation.md
deckbuilder/assets/templates/default.pptx
deckbuilder/cli/__init__.py
deckbuilder/cli/__main__.py
deckbuilder/cli/commands.py
deckbuilder/cli/main.py
deckbuilder/cli/naming_conventions.py
deckbuilder/content/__init__.py
deckbuilder/content/formatter.py
deckbuilder/content/formatting_support.py
deckbuilder/content/frontmatter_to_json_converter.py
deckbuilder/content/matcher.py
deckbuilder/content/placeholder_types.py
deckbuilder/content/processor.py
deckbuilder/content/table_integration.py
deckbuilder/content/table_parser.py
deckbuilder/core/__init__.py
deckbuilder/core/content_processor.py
deckbuilder/core/engine.py
deckbuilder/core/field_processor.py
deckbuilder/core/layout_resolver.py
deckbuilder/core/placeholder_resolver.py
deckbuilder/core/presentation_builder.py
deckbuilder/core/slide_builder.py
deckbuilder/core/slide_coordinator.py
deckbuilder/core/table_builder.py
deckbuilder/core/table_handler.py
deckbuilder/core/validation.py
deckbuilder/image/__init__.py
deckbuilder/image/image_handler.py
deckbuilder/image/placeholder.py
deckbuilder/image/placekitten_integration.py
deckbuilder/language_mappings/en-AU.json
deckbuilder/language_mappings/en-GB.json
deckbuilder/language_mappings/en-NZ.json
deckbuilder/language_mappings/en-US.json
deckbuilder/refactor/layout_resolver.py
deckbuilder/refactor/placeholder_manager.py
deckbuilder/refactor/placeholder_normalizer.py
deckbuilder/structured_frontmatter_patterns/agenda_6_textboxes.json
deckbuilder/structured_frontmatter_patterns/before_and_after.json
deckbuilder/structured_frontmatter_patterns/big_number.json
deckbuilder/structured_frontmatter_patterns/blank.json
deckbuilder/structured_frontmatter_patterns/comparison.json
deckbuilder-1.4.1.dist-info/licenses/LICENSE
deckbuilder-1.4.1.dist-info/METADATA
deckbuilder-1.4.1.dist-info/WHEEL
deckbuilder-1.4.1.dist-info/entry_points.txt
deckbuilder-1.4.1.dist-info/top_level.txt
deckbuilder-1.4.1.dist-info/RECORD
