Metadata-Version: 2.4
Name: deckbuilder
Version: 1.4.1
Summary: Microsoft PowerPoint, presentation slide library, MCP server and CLI tools. Designed for LLM generation of PPTX slides.
Author: Bruce McLeod
License: Apache-2.0
Project-URL: Homepage, https://github.com/teknologika/deckbuilder
Project-URL: Repository, https://github.com/teknologika/deckbuilder.git
Project-URL: Issues, https://github.com/teknologika/deckbuilder/issues
Project-URL: Documentation, https://github.com/teknologika/deckbuilder/blob/main/README.md
Project-URL: Changelog, https://github.com/teknologika/deckbuilder/releases
Project-URL: Bug Reports, https://github.com/teknologika/deckbuilder/issues
Project-URL: Source Code, https://github.com/teknologika/deckbuilder
Keywords: mcp,powerpoint,presentations,automation,content-first,template-management,image-processing,cli
Classifier: Development Status :: 4 - Beta
Classifier: Intended Audience :: End Users/Desktop
Classifier: Intended Audience :: Developers
Classifier: License :: OSI Approved :: Apache Software License
Classifier: Programming Language :: Python :: 3
Classifier: Programming Language :: Python :: 3.11
Classifier: Programming Language :: Python :: 3.12
Classifier: Programming Language :: Python :: 3.13
Classifier: Topic :: Office/Business :: Office Suites
Classifier: Topic :: Software Development :: Libraries :: Python Modules
Classifier: Topic :: Multimedia :: Graphics :: Graphics Conversion
Classifier: Topic :: Scientific/Engineering :: Artificial Intelligence
Classifier: Environment :: Console
Classifier: Operating System :: OS Independent
Requires-Python: >=3.11
License-File: LICENSE
Requires-Dist: fastmcp>=0.3.0
Requires-Dist: python-pptx>=1.0.0
Requires-Dist: python-dotenv>=1.0.0
Requires-Dist: pyyaml>=6.0.0
Requires-Dist: opencv-python>=4.8.0
Requires-Dist: Pillow>=10.0.0
Requires-Dist: numpy>=1.24.0
Requires-Dist: click>=8.0.0
Requires-Dist: webcolors>=1.13.0
Provides-Extra: test
Requires-Dist: pytest>=7.0.0; extra == "test"
Requires-Dist: pytest-cov>=4.0.0; extra == "test"
Requires-Dist: pytest-mock>=3.10.0; extra == "test"
Requires-Dist: pytest-xdist>=3.0.0; extra == "test"
Requires-Dist: pytest-html>=3.0.0; extra == "test"
Requires-Dist: pytest-asyncio>=0.21.0; extra == "test"
Provides-Extra: lint
Requires-Dist: flake8>=5.0.0; extra == "lint"
Requires-Dist: flake8-length>=0.3.0; extra == "lint"
Requires-Dist: bandit>=1.7.5; extra == "lint"
Provides-Extra: format
Requires-Dist: black>=22.0.0; extra == "format"
Provides-Extra: docs
Requires-Dist: mkdocs>=1.6.1; extra == "docs"
Requires-Dist: mkdocs-material>=9.6.16; extra == "docs"
Requires-Dist: mkdocstrings[python]>=0.30.0; extra == "docs"
Requires-Dist: mkdocs-click>=0.9.0; extra == "docs"
Requires-Dist: pymdown-extensions>=10.16.1; extra == "docs"
Provides-Extra: dev
Requires-Dist: deckbuilder[docs,format,lint,test]; extra == "dev"
Requires-Dist: tomli>=2.0.1; extra == "dev"
Requires-Dist: black[jupyter]>=24.4.0; extra == "dev"
Dynamic: license-file
